hmd_lang_naming/__init__.py
hmd_lang_naming/hmd_lang_naming_client.py
hmd_lang_naming/service.py
hmd_lang_naming/service_consists_of_repo_instance_deployment.py
hmd_lang_naming/service_is_in_environment.py
hmd_lang_naming/schemas/hmd_lang_naming/service.hms
hmd_lang_naming/schemas/hmd_lang_naming/service_consists_of_repo_instance_deployment.hms
hmd_lang_naming/schemas/hmd_lang_naming/service_is_in_environment.hms
hmd_lang_naming-0.1.13.dist-info/METADATA
hmd_lang_naming-0.1.13.dist-info/WHEEL
hmd_lang_naming-0.1.13.dist-info/top_level.txt
hmd_lang_naming-0.1.13.dist-info/RECORD
